models/__init__.py
models/base.py
models/cars.py
models/db_settings.py
models/properties.py
unegui_models-0.1.8.dist-info/METADATA
unegui_models-0.1.8.dist-info/WHEEL
unegui_models-0.1.8.dist-info/top_level.txt
unegui_models-0.1.8.dist-info/RECORD
